{
	"info": {
		"_postman_id": "997b80be-0f36-415f-a206-96ba70726543",
		"name": "Curso Backend",
		"schema": "https://schema.getpostman.com/json/collection/v2.1.0/collection.json"
	},
	"item": [
		{
			"name": "Productos",
			"item": [
				{
					"name": "Obtiene todos los productos",
					"request": {
						"method": "GET",
						"header": [],
						"url": {
							"raw": "http://localhost:8080/api/productos",
							"protocol": "http",
							"host": [
								"localhost"
							],
							"port": "8080",
							"path": [
								"api",
								"productos"
							]
						}
					},
					"response": []
				},
				{
					"name": "Obtiene un producto",
					"request": {
						"method": "GET",
						"header": [],
						"url": {
							"raw": "http://localhost:8080/api/productos/2",
							"protocol": "http",
							"host": [
								"localhost"
							],
							"port": "8080",
							"path": [
								"api",
								"productos",
								"2"
							]
						}
					},
					"response": []
				},
				{
					"name": "Crea un producto_1",
					"request": {
						"method": "POST",
						"header": [],
						"body": {
							"mode": "raw",
							"raw": "    {\r\n      \"nombre\": \"Balanza\",\r\n      \"descripcion\": \"Balanza que sirve para medir la fuerza que ejerce la gravedad sobre una masa\",\r\n      \"codigo\": 10001,\r\n      \"foto\": \"https://encrypted-tbn0.gstatic.com/images?q=tbn:ANd9GcT6acDJjcj_HlIq55Oa7Lahq-wcVY9MT-yo5HPOFuQIz0ynLYHs4Ip5oEySn_OZ2BjjbYA&usqp=CAU\",\r\n      \"precio\": 6000,\r\n      \"stock\": 4\r\n    }",
							"options": {
								"raw": {
									"language": "json"
								}
							}
						},
						"url": {
							"raw": "http://localhost:8080/api/productos",
							"protocol": "http",
							"host": [
								"localhost"
							],
							"port": "8080",
							"path": [
								"api",
								"productos"
							]
						}
					},
					"response": []
				},
				{
					"name": "Crea un producto_2",
					"request": {
						"method": "POST",
						"header": [],
						"body": {
							"mode": "raw",
							"raw": "    {\r\n      \"nombre\": \"Taza\",\r\n      \"descripcion\": \"Taza para tomar el té\",\r\n      \"codigo\": 30002,\r\n      \"foto\": \"https://i.pinimg.com/originals/0a/5c/f7/0a5cf7146ae2426614af1e8e6ea4353b.jpg\",\r\n      \"precio\": 900,\r\n      \"stock\": 40\r\n    }",
							"options": {
								"raw": {
									"language": "json"
								}
							}
						},
						"url": {
							"raw": "http://localhost:8080/api/productos",
							"protocol": "http",
							"host": [
								"localhost"
							],
							"port": "8080",
							"path": [
								"api",
								"productos"
							]
						}
					},
					"response": []
				},
				{
					"name": "Actualizar producto",
					"request": {
						"method": "PUT",
						"header": [],
						"body": {
							"mode": "raw",
							"raw": "    {\r\n      \"nombre\": \"Vaso\",\r\n      \"descripcion\": \"Vaso para tomar agua\",\r\n      \"codigo\": 30004,\r\n      \"foto\": \"https://encrypted-tbn0.gstatic.com/images?q=tbn:ANd9GcQqzd2dbiIkMKmkhzSoop8LDa7-KRZEgeTh7g&usqp=CAU\",\r\n      \"precio\": 500,\r\n      \"stock\": 100\r\n    }",
							"options": {
								"raw": {
									"language": "json"
								}
							}
						},
						"url": {
							"raw": "http://localhost:8080/api/productos/2",
							"protocol": "http",
							"host": [
								"localhost"
							],
							"port": "8080",
							"path": [
								"api",
								"productos",
								"2"
							]
						}
					},
					"response": []
				},
				{
					"name": "Borrar producto",
					"request": {
						"method": "DELETE",
						"header": [],
						"url": {
							"raw": "http://localhost:8080/api/productos/6",
							"protocol": "http",
							"host": [
								"localhost"
							],
							"port": "8080",
							"path": [
								"api",
								"productos",
								"6"
							]
						}
					},
					"response": []
				}
			]
		},
		{
			"name": "Carrito",
			"item": [
				{
					"name": "Obtener productos del carrito Copy",
					"request": {
						"method": "GET",
						"header": [],
						"url": {
							"raw": "http://localhost:8080/api/carrito/4/productos",
							"protocol": "http",
							"host": [
								"localhost"
							],
							"port": "8080",
							"path": [
								"api",
								"carrito",
								"4",
								"productos"
							]
						}
					},
					"response": []
				},
				{
					"name": "Crear carrito",
					"request": {
						"method": "POST",
						"header": [],
						"url": {
							"raw": "http://localhost:8080/api/carrito",
							"protocol": "http",
							"host": [
								"localhost"
							],
							"port": "8080",
							"path": [
								"api",
								"carrito"
							]
						}
					},
					"response": []
				},
				{
					"name": "Agregar producto a un carrito",
					"request": {
						"method": "POST",
						"header": [],
						"url": {
							"raw": "http://localhost:8080/api/carrito/1/productos/5",
							"protocol": "http",
							"host": [
								"localhost"
							],
							"port": "8080",
							"path": [
								"api",
								"carrito",
								"1",
								"productos",
								"5"
							]
						}
					},
					"response": []
				},
				{
					"name": "Borrar producto de carrito",
					"request": {
						"method": "DELETE",
						"header": [],
						"url": {
							"raw": "http://localhost:8080/api/carrito/2/productos/2",
							"protocol": "http",
							"host": [
								"localhost"
							],
							"port": "8080",
							"path": [
								"api",
								"carrito",
								"2",
								"productos",
								"2"
							]
						}
					},
					"response": []
				},
				{
					"name": "Borrar carrito Copy",
					"request": {
						"method": "DELETE",
						"header": [],
						"url": {
							"raw": "http://localhost:8080/api/carrito/2",
							"protocol": "http",
							"host": [
								"localhost"
							],
							"port": "8080",
							"path": [
								"api",
								"carrito",
								"2"
							]
						}
					},
					"response": []
				}
			]
		}
	]
}